palabra_ai/__init__.py
palabra_ai/audio.py
palabra_ai/client.py
palabra_ai/config.py
palabra_ai/constant.py
palabra_ai/enum.py
palabra_ai/exc.py
palabra_ai/lang.py
palabra_ai/message.py
palabra_ai/model.py
palabra_ai/py.typed
palabra_ai/types.py
palabra_ai/benchmark/__init__.py
palabra_ai/benchmark/__main__.py
palabra_ai/benchmark/report.py
palabra_ai/benchmark/rewind.py
palabra_ai/benchmark/utils.py
palabra_ai/debug/__init__.py
palabra_ai/debug/hang_coroutines.py
palabra_ai/experimental/__init__.py
palabra_ai/experimental/file2file_webrtc.py
palabra_ai/experimental/file2file_ws.py
palabra_ai/internal/__init__.py
palabra_ai/internal/audio.py
palabra_ai/internal/device.py
palabra_ai/internal/rest.py
palabra_ai/task/__init__.py
palabra_ai/task/base.py
palabra_ai/task/logger.py
palabra_ai/task/manager.py
palabra_ai/task/stat.py
palabra_ai/task/transcription.py
palabra_ai/task/adapter/__init__.py
palabra_ai/task/adapter/base.py
palabra_ai/task/adapter/buffer.py
palabra_ai/task/adapter/device.py
palabra_ai/task/adapter/dummy.py
palabra_ai/task/adapter/file.py
palabra_ai/task/io/__init__.py
palabra_ai/task/io/base.py
palabra_ai/task/io/webrtc.py
palabra_ai/task/io/ws.py
palabra_ai/util/__init__.py
palabra_ai/util/aio.py
palabra_ai/util/capped_set.py
palabra_ai/util/differ.py
palabra_ai/util/emoji.py
palabra_ai/util/fanout_queue.py
palabra_ai/util/iterables.py
palabra_ai/util/logger.py
palabra_ai/util/orjson.py
palabra_ai/util/pydantic.py
palabra_ai/util/sysinfo.py
palabra_ai/util/timing.py
palabra_ai-0.6.8.dist-info/METADATA
palabra_ai-0.6.8.dist-info/WHEEL
palabra_ai-0.6.8.dist-info/licenses/LICENSE
palabra_ai-0.6.8.dist-info/RECORD
