Metadata-Version: 2.4
Name: palabra-ai
Version: 0.6.8
Summary: Client library for Palabra AI's real-time speech translation, dubbing, and voice synthesis APIs across 25+ languages.
Project-URL: Homepage, https://palabra.ai
Project-URL: Repository, https://github.com/PalabraAI/palabra-ai-python
Project-URL: Documentation, https://docs.palabra.ai
Project-URL: Issues, https://github.com/PalabraAI/palabra-ai-python/issues
Author-email: Andrei Kobyshev <a.kobyshev@palabra.ai>
License-Expression: MIT
License-File: LICENSE
Keywords: api-client,dubbing,palabra-ai,speech-translation,voice-synthesis
Classifier: License :: OSI Approved :: MIT License
Classifier: Operating System :: OS Independent
Classifier: Programming Language :: Python :: 3
Classifier: Programming Language :: Python :: 3.11
Classifier: Programming Language :: Python :: 3.12
Classifier: Programming Language :: Python :: 3.13
Classifier: Topic :: Communications
Classifier: Topic :: Software Development :: Libraries :: Python Modules
Classifier: Topic :: Text Processing :: Linguistic
Requires-Python: <4.0,>=3.11
Requires-Dist: aiofile<4,>=3.8
Requires-Dist: aiohttp<4,>=3.9
Requires-Dist: aioshutdown>=0.0.4
Requires-Dist: av>=13.0.0
Requires-Dist: certifi>=2023.0.0
Requires-Dist: environs<14.2,>=14.1
Requires-Dist: httpx>=0.28.1
Requires-Dist: jinja2>=3.1.0
Requires-Dist: librosa>=0.10.2
Requires-Dist: livekit<2,>=1.0.11
Requires-Dist: loguru>=0.7.3
Requires-Dist: numpy>=1.24
Requires-Dist: orjson<4,>=3.8
Requires-Dist: prettytable>=3.16.0
Requires-Dist: pydantic<3,>=2
Requires-Dist: pyloudnorm>=0.1.1
Requires-Dist: sounddevice<1,>=0.5.1
Requires-Dist: tqdm>=4.66.0
Requires-Dist: uvloop>=0.17
Requires-Dist: wat>=0.6.0
Requires-Dist: websockets<16,>=13
